Compiled from "AbstractClientPlayerEntityMixin.java"
public abstract class com.github.razorplay01.cpa.mixin.AbstractClientPlayerEntityMixin extends net.minecraft.class_1657 implements com.github.razorplay01.cpa.platform.common.util.interfaces.IAnimationControl,com.github.razorplay01.cpa.platform.common.util.interfaces.ICustomAnimatedPlayer {
  private com.github.razorplay01.cpa.platform.common.animation.AnimationContainer mainAnimationContainer;

  private com.github.razorplay01.cpa.platform.common.animation.AnimationContainer overlayAnimationContainer;

  private com.github.razorplay01.cpa.platform.common.animation.AnimationContainer specialAnimationContainer;

  private final com.github.razorplay01.cpa.platform.common.util.PlayerData playerData;

  private com.github.razorplay01.cpa.platform.common.util.records.AnimationContext actualAnimationContext;

  protected com.github.razorplay01.cpa.mixin.AbstractClientPlayerEntityMixin(net.minecraft.class_1937, com.mojang.authlib.GameProfile);
    Code:
       0: aload_0
       1: aload_1
       2: aload_2
       3: invokespecial #42                 // Method net/minecraft/class_1657."<init>":(Lnet/minecraft/class_1937;Lcom/mojang/authlib/GameProfile;)V
       6: aload_0
       7: new           #44                 // class com/github/razorplay01/cpa/platform/common/util/PlayerData
      10: dup
      11: invokespecial #47                 // Method com/github/razorplay01/cpa/platform/common/util/PlayerData."<init>":()V
      14: putfield      #49                 // Field playerData:Lcom/github/razorplay01/cpa/platform/common/util/PlayerData;
      17: return

  private void init(net.minecraft.class_638, com.mojang.authlib.GameProfile, org.spongepowered.asm.mixin.injection.callback.CallbackInfo);
    Code:
       0: aload_0
       1: new           #64                 // class com/github/razorplay01/cpa/platform/common/animation/AnimationContainer
       4: dup
       5: aload_0
       6: checkcast     #66                 // class net/minecraft/class_742
       9: getstatic     #72                 // Field com/github/razorplay01/cpa/ModTemplate.MAIN_ANIMATION_CONTAINER_LAYER_ID:Lnet/minecraft/class_2960;
      12: invokestatic  #78                 // Method com/zigythebird/playeranim/api/PlayerAnimationAccess.getPlayerAnimationLayer:(Lnet/minecraft/class_11890;Lnet/minecraft/class_2960;)Lcom/zigythebird/playeranimcore/animation/layered/IAnimation;
      15: checkcast     #80                 // class com/zigythebird/playeranimcore/animation/AnimationController
      18: new           #82                 // class java/util/HashMap
      21: dup
      22: getstatic     #88                 // Field com/github/razorplay01/cpa/platform/common/util/enums/Modifiers.MIRROR_MODIFIER:Lcom/github/razorplay01/cpa/platform/common/util/enums/Modifiers;
      25: invokevirtual #92                 // Method com/github/razorplay01/cpa/platform/common/util/enums/Modifiers.getModifierId:()Ljava/lang/String;
      28: new           #94                 // class com/zigythebird/playeranimcore/animation/layered/modifier/MirrorModifier
      31: dup
      32: invokespecial #95                 // Method com/zigythebird/playeranimcore/animation/layered/modifier/MirrorModifier."<init>":()V
      35: getstatic     #98                 // Field com/github/razorplay01/cpa/platform/common/util/enums/Modifiers.SPEED_MODIFIER:Lcom/github/razorplay01/cpa/platform/common/util/enums/Modifiers;
      38: invokevirtual #92                 // Method com/github/razorplay01/cpa/platform/common/util/enums/Modifiers.getModifierId:()Ljava/lang/String;
      41: new           #100                // class com/zigythebird/playeranimcore/animation/layered/modifier/SpeedModifier
      44: dup
      45: fconst_1
      46: invokespecial #103                // Method com/zigythebird/playeranimcore/animation/layered/modifier/SpeedModifier."<init>":(F)V
      49: getstatic     #106                // Field com/github/razorplay01/cpa/platform/common/util/enums/Modifiers.ADJUSTMENT_MODIFIER:Lcom/github/razorplay01/cpa/platform/common/util/enums/Modifiers;
      52: invokevirtual #92                 // Method com/github/razorplay01/cpa/platform/common/util/enums/Modifiers.getModifierId:()Ljava/lang/String;
      55: aload_0
      56: checkcast     #66                 // class net/minecraft/class_742
      59: invokestatic  #112                // Method com/github/razorplay01/cpa/platform/common/util/CustomModifiers.createLeanModifier:(Lnet/minecraft/class_11890;)Lcom/zigythebird/playeranimcore/animation/layered/modifier/AdjustmentModifier;
      62: invokestatic  #118                // InterfaceMethod java/util/Map.of:(Ljava/lang/Object;Ljava/lang/Object;Ljava/lang/Object;Ljava/lang/Object;Ljava/lang/Object;Ljava/lang/Object;)Ljava/util/Map;
      65: invokespecial #121                // Method java/util/HashMap."<init>":(Ljava/util/Map;)V
      68: getstatic     #127                // Field com/github/razorplay01/cpa/platform/common/util/enums/AnimationsId.BLANK_LOOP_ANIMATION:Lcom/github/razorplay01/cpa/platform/common/util/enums/AnimationsId;
      71: invokevirtual #130                // Method com/github/razorplay01/cpa/platform/common/util/enums/AnimationsId.getAnimationId:()Ljava/lang/String;
      74: invokestatic  #134                // Method com/github/razorplay01/cpa/ModTemplate.getAnimation:(Ljava/lang/String;)Lcom/zigythebird/playeranimcore/animation/Animation;
      77: getstatic     #127                // Field com/github/razorplay01/cpa/platform/common/util/enums/AnimationsId.BLANK_LOOP_ANIMATION:Lcom/github/razorplay01/cpa/platform/common/util/enums/AnimationsId;
      80: invokevirtual #130                // Method com/github/razorplay01/cpa/platform/common/util/enums/AnimationsId.getAnimationId:()Ljava/lang/String;
      83: ldc           #136                // String
      85: iconst_0
      86: iconst_0
      87: iconst_0
      88: fconst_0
      89: invokespecial #139                // Method com/github/razorplay01/cpa/platform/common/animation/AnimationContainer."<init>":(Lcom/zigythebird/playeranimcore/animation/AnimationController;Ljava/util/HashMap;Lcom/zigythebird/playeranimcore/animation/Animation;Ljava/lang/String;Ljava/lang/String;IIIF)V
      92: putfield      #141                // Field mainAnimationContainer:Lcom/github/razorplay01/cpa/platform/common/animation/AnimationContainer;
      95: aload_0
      96: new           #64                 // class com/github/razorplay01/cpa/platform/common/animation/AnimationContainer
      99: dup
     100: aload_0
     101: checkcast     #66                 // class net/minecraft/class_742
     104: getstatic     #144                // Field com/github/razorplay01/cpa/ModTemplate.OVERLAY_ANIMATION_CONTAINER_LAYER_ID:Lnet/minecraft/class_2960;
     107: invokestatic  #78                 // Method com/zigythebird/playeranim/api/PlayerAnimationAccess.getPlayerAnimationLayer:(Lnet/minecraft/class_11890;Lnet/minecraft/class_2960;)Lcom/zigythebird/playeranimcore/animation/layered/IAnimation;
     110: checkcast     #80                 // class com/zigythebird/playeranimcore/animation/AnimationController
     113: new           #82                 // class java/util/HashMap
     116: dup
     117: getstatic     #88                 // Field com/github/razorplay01/cpa/platform/common/util/enums/Modifiers.MIRROR_MODIFIER:Lcom/github/razorplay01/cpa/platform/common/util/enums/Modifiers;
     120: invokevirtual #92                 // Method com/github/razorplay01/cpa/platform/common/util/enums/Modifiers.getModifierId:()Ljava/lang/String;
     123: new           #94                 // class com/zigythebird/playeranimcore/animation/layered/modifier/MirrorModifier
     126: dup
     127: invokespecial #95                 // Method com/zigythebird/playeranimcore/animation/layered/modifier/MirrorModifier."<init>":()V
     130: getstatic     #98                 // Field com/github/razorplay01/cpa/platform/common/util/enums/Modifiers.SPEED_MODIFIER:Lcom/github/razorplay01/cpa/platform/common/util/enums/Modifiers;
     133: invokevirtual #92                 // Method com/github/razorplay01/cpa/platform/common/util/enums/Modifiers.getModifierId:()Ljava/lang/String;
     136: new           #100                // class com/zigythebird/playeranimcore/animation/layered/modifier/SpeedModifier
     139: dup
     140: fconst_1
     141: invokespecial #103                // Method com/zigythebird/playeranimcore/animation/layered/modifier/SpeedModifier."<init>":(F)V
     144: getstatic     #147                // Field com/github/razorplay01/cpa/platform/common/util/enums/Modifiers.SHIELD_MODIFIER:Lcom/github/razorplay01/cpa/platform/common/util/enums/Modifiers;
     147: invokevirtual #92                 // Method com/github/razorplay01/cpa/platform/common/util/enums/Modifiers.getModifierId:()Ljava/lang/String;
     150: aload_0
     151: checkcast     #66                 // class net/minecraft/class_742
     154: invokestatic  #150                // Method com/github/razorplay01/cpa/platform/common/util/CustomModifiers.createShieldModifier:(Lnet/minecraft/class_11890;)Lcom/zigythebird/playeranimcore/animation/layered/modifier/AdjustmentModifier;
     157: getstatic     #153                // Field com/github/razorplay01/cpa/platform/common/util/enums/Modifiers.HAND_SWING_MODIFIER:Lcom/github/razorplay01/cpa/platform/common/util/enums/Modifiers;
     160: invokevirtual #92                 // Method com/github/razorplay01/cpa/platform/common/util/enums/Modifiers.getModifierId:()Ljava/lang/String;
     163: aload_0
     164: checkcast     #66                 // class net/minecraft/class_742
     167: aload_0
     168: getfield      #141                // Field mainAnimationContainer:Lcom/github/razorplay01/cpa/platform/common/animation/AnimationContainer;
     171: invokestatic  #157                // Method com/github/razorplay01/cpa/platform/common/util/CustomModifiers.createSwingModifier:(Lnet/minecraft/class_11890;Lcom/github/razorplay01/cpa/platform/common/animation/AnimationContainer;)Lcom/zigythebird/playeranimcore/animation/layered/modifier/AdjustmentModifier;
     174: getstatic     #160                // Field com/github/razorplay01/cpa/platform/common/util/enums/Modifiers.BOW_MODIFIER:Lcom/github/razorplay01/cpa/platform/common/util/enums/Modifiers;
     177: invokevirtual #92                 // Method com/github/razorplay01/cpa/platform/common/util/enums/Modifiers.getModifierId:()Ljava/lang/String;
     180: aload_0
     181: checkcast     #66                 // class net/minecraft/class_742
     184: invokestatic  #163                // Method com/github/razorplay01/cpa/platform/common/util/CustomModifiers.createBowModifier:(Lnet/minecraft/class_11890;)Lcom/zigythebird/playeranimcore/animation/layered/modifier/AdjustmentModifier;
     187: invokestatic  #166                // InterfaceMethod java/util/Map.of:(Ljava/lang/Object;Ljava/lang/Object;Ljava/lang/Object;Ljava/lang/Object;Ljava/lang/Object;Ljava/lang/Object;Ljava/lang/Object;Ljava/lang/Object;Ljava/lang/Object;Ljava/lang/Object;)Ljava/util/Map;
     190: invokespecial #121                // Method java/util/HashMap."<init>":(Ljava/util/Map;)V
     193: getstatic     #127                // Field com/github/razorplay01/cpa/platform/common/util/enums/AnimationsId.BLANK_LOOP_ANIMATION:Lcom/github/razorplay01/cpa/platform/common/util/enums/AnimationsId;
     196: invokevirtual #130                // Method com/github/razorplay01/cpa/platform/common/util/enums/AnimationsId.getAnimationId:()Ljava/lang/String;
     199: invokestatic  #134                // Method com/github/razorplay01/cpa/ModTemplate.getAnimation:(Ljava/lang/String;)Lcom/zigythebird/playeranimcore/animation/Animation;
     202: getstatic     #127                // Field com/github/razorplay01/cpa/platform/common/util/enums/AnimationsId.BLANK_LOOP_ANIMATION:Lcom/github/razorplay01/cpa/platform/common/util/enums/AnimationsId;
     205: invokevirtual #130                // Method com/github/razorplay01/cpa/platform/common/util/enums/AnimationsId.getAnimationId:()Ljava/lang/String;
     208: ldc           #136                // String
     210: iconst_0
     211: iconst_0
     212: iconst_0
     213: fconst_0
     214: invokespecial #139                // Method com/github/razorplay01/cpa/platform/common/animation/AnimationContainer."<init>":(Lcom/zigythebird/playeranimcore/animation/AnimationController;Ljava/util/HashMap;Lcom/zigythebird/playeranimcore/animation/Animation;Ljava/lang/String;Ljava/lang/String;IIIF)V
     217: putfield      #168                // Field overlayAnimationContainer:Lcom/github/razorplay01/cpa/platform/common/animation/AnimationContainer;
     220: aload_0
     221: new           #64                 // class com/github/razorplay01/cpa/platform/common/animation/AnimationContainer
     224: dup
     225: aload_0
     226: checkcast     #66                 // class net/minecraft/class_742
     229: getstatic     #171                // Field com/github/razorplay01/cpa/ModTemplate.SPECIAL_ANIMATION_CONTAINER_LAYER_ID:Lnet/minecraft/class_2960;
     232: invokestatic  #78                 // Method com/zigythebird/playeranim/api/PlayerAnimationAccess.getPlayerAnimationLayer:(Lnet/minecraft/class_11890;Lnet/minecraft/class_2960;)Lcom/zigythebird/playeranimcore/animation/layered/IAnimation;
     235: checkcast     #80                 // class com/zigythebird/playeranimcore/animation/AnimationController
     238: new           #82                 // class java/util/HashMap
     241: dup
     242: getstatic     #88                 // Field com/github/razorplay01/cpa/platform/common/util/enums/Modifiers.MIRROR_MODIFIER:Lcom/github/razorplay01/cpa/platform/common/util/enums/Modifiers;
     245: invokevirtual #92                 // Method com/github/razorplay01/cpa/platform/common/util/enums/Modifiers.getModifierId:()Ljava/lang/String;
     248: new           #94                 // class com/zigythebird/playeranimcore/animation/layered/modifier/MirrorModifier
     251: dup
     252: invokespecial #95                 // Method com/zigythebird/playeranimcore/animation/layered/modifier/MirrorModifier."<init>":()V
     255: getstatic     #98                 // Field com/github/razorplay01/cpa/platform/common/util/enums/Modifiers.SPEED_MODIFIER:Lcom/github/razorplay01/cpa/platform/common/util/enums/Modifiers;
     258: invokevirtual #92                 // Method com/github/razorplay01/cpa/platform/common/util/enums/Modifiers.getModifierId:()Ljava/lang/String;
     261: new           #100                // class com/zigythebird/playeranimcore/animation/layered/modifier/SpeedModifier
     264: dup
     265: fconst_1
     266: invokespecial #103                // Method com/zigythebird/playeranimcore/animation/layered/modifier/SpeedModifier."<init>":(F)V
     269: invokestatic  #174                // InterfaceMethod java/util/Map.of:(Ljava/lang/Object;Ljava/lang/Object;Ljava/lang/Object;Ljava/lang/Object;)Ljava/util/Map;
     272: invokespecial #121                // Method java/util/HashMap."<init>":(Ljava/util/Map;)V
     275: getstatic     #127                // Field com/github/razorplay01/cpa/platform/common/util/enums/AnimationsId.BLANK_LOOP_ANIMATION:Lcom/github/razorplay01/cpa/platform/common/util/enums/AnimationsId;
     278: invokevirtual #130                // Method com/github/razorplay01/cpa/platform/common/util/enums/AnimationsId.getAnimationId:()Ljava/lang/String;
     281: invokestatic  #134                // Method com/github/razorplay01/cpa/ModTemplate.getAnimation:(Ljava/lang/String;)Lcom/zigythebird/playeranimcore/animation/Animation;
     284: getstatic     #127                // Field com/github/razorplay01/cpa/platform/common/util/enums/AnimationsId.BLANK_LOOP_ANIMATION:Lcom/github/razorplay01/cpa/platform/common/util/enums/AnimationsId;
     287: invokevirtual #130                // Method com/github/razorplay01/cpa/platform/common/util/enums/AnimationsId.getAnimationId:()Ljava/lang/String;
     290: ldc           #136                // String
     292: iconst_0
     293: iconst_0
     294: iconst_0
     295: fconst_0
     296: invokespecial #139                // Method com/github/razorplay01/cpa/platform/common/animation/AnimationContainer."<init>":(Lcom/zigythebird/playeranimcore/animation/AnimationController;Ljava/util/HashMap;Lcom/zigythebird/playeranimcore/animation/Animation;Ljava/lang/String;Ljava/lang/String;IIIF)V
     299: putfield      #176                // Field specialAnimationContainer:Lcom/github/razorplay01/cpa/platform/common/animation/AnimationContainer;
     302: aload_0
     303: getfield      #141                // Field mainAnimationContainer:Lcom/github/razorplay01/cpa/platform/common/animation/AnimationContainer;
     306: invokestatic  #182                // Method com/github/razorplay01/cpa/platform/common/util/Util.addModifiersToContainer:(Lcom/github/razorplay01/cpa/platform/common/animation/AnimationContainer;)V
     309: aload_0
     310: getfield      #168                // Field overlayAnimationContainer:Lcom/github/razorplay01/cpa/platform/common/animation/AnimationContainer;
     313: invokestatic  #182                // Method com/github/razorplay01/cpa/platform/common/util/Util.addModifiersToContainer:(Lcom/github/razorplay01/cpa/platform/common/animation/AnimationContainer;)V
     316: aload_0
     317: getfield      #176                // Field specialAnimationContainer:Lcom/github/razorplay01/cpa/platform/common/animation/AnimationContainer;
     320: invokestatic  #182                // Method com/github/razorplay01/cpa/platform/common/util/Util.addModifiersToContainer:(Lcom/github/razorplay01/cpa/platform/common/animation/AnimationContainer;)V
     323: return

  public void tick(org.spongepowered.asm.mixin.injection.callback.CallbackInfo);
    Code:
       0: aload_0
       1: getfield      #141                // Field mainAnimationContainer:Lcom/github/razorplay01/cpa/platform/common/animation/AnimationContainer;
       4: ifnull        21
       7: aload_0
       8: getfield      #168                // Field overlayAnimationContainer:Lcom/github/razorplay01/cpa/platform/common/animation/AnimationContainer;
      11: ifnull        21
      14: aload_0
      15: getfield      #176                // Field specialAnimationContainer:Lcom/github/razorplay01/cpa/platform/common/animation/AnimationContainer;
      18: ifnonnull     22
      21: return
      22: aload_0
      23: getfield      #49                 // Field playerData:Lcom/github/razorplay01/cpa/platform/common/util/PlayerData;
      26: aload_0
      27: checkcast     #66                 // class net/minecraft/class_742
      30: invokevirtual #191                // Method com/github/razorplay01/cpa/platform/common/util/PlayerData.update:(Lnet/minecraft/class_11890;)V
      33: aload_0
      34: invokevirtual #194                // Method enableAllBodyPartsInAllContainers:()V
      37: aload_0
      38: getfield      #168                // Field overlayAnimationContainer:Lcom/github/razorplay01/cpa/platform/common/animation/AnimationContainer;
      41: invokevirtual #197                // Method com/github/razorplay01/cpa/platform/common/animation/AnimationContainer.resetAnimationProperties:()V
      44: aload_0
      45: new           #199                // class com/github/razorplay01/cpa/platform/common/util/records/AnimationContext
      48: dup
      49: aload_0
      50: getfield      #141                // Field mainAnimationContainer:Lcom/github/razorplay01/cpa/platform/common/animation/AnimationContainer;
      53: aload_0
      54: getfield      #168                // Field overlayAnimationContainer:Lcom/github/razorplay01/cpa/platform/common/animation/AnimationContainer;
      57: aload_0
      58: getfield      #176                // Field specialAnimationContainer:Lcom/github/razorplay01/cpa/platform/common/animation/AnimationContainer;
      61: aload_0
      62: checkcast     #66                 // class net/minecraft/class_742
      65: aload_0
      66: getfield      #49                 // Field playerData:Lcom/github/razorplay01/cpa/platform/common/util/PlayerData;
      69: aload_0
      70: aload_0
      71: invokespecial #202                // Method com/github/razorplay01/cpa/platform/common/util/records/AnimationContext."<init>":(Lcom/github/razorplay01/cpa/platform/common/animation/AnimationContainer;Lcom/github/razorplay01/cpa/platform/common/animation/AnimationContainer;Lcom/github/razorplay01/cpa/platform/common/animation/AnimationContainer;Lnet/minecraft/class_11890;Lcom/github/razorplay01/cpa/platform/common/util/PlayerData;Lcom/github/razorplay01/cpa/platform/common/util/interfaces/IAnimationControl;Lcom/github/razorplay01/cpa/platform/common/util/interfaces/ICustomAnimatedPlayer;)V
      74: putfield      #204                // Field actualAnimationContext:Lcom/github/razorplay01/cpa/platform/common/util/records/AnimationContext;
      77: aload_0
      78: invokevirtual #207                // Method playAnimations:()V
      81: aload_0
      82: invokevirtual #210                // Method updateAnimationSpeeds:()V
      85: aload_0
      86: invokevirtual #213                // Method checkMainHandItemForArmDisabling:()V
      89: aload_0
      90: invokevirtual #216                // Method checkOffHandItemForArmDisabling:()V
      93: aload_0
      94: invokevirtual #219                // Method applyDisables:()V
      97: aload_0
      98: invokevirtual #222                // Method updateAnimationContainers:()V
     101: aload_0
     102: getfield      #49                 // Field playerData:Lcom/github/razorplay01/cpa/platform/common/util/PlayerData;
     105: aload_0
     106: getfield      #49                 // Field playerData:Lcom/github/razorplay01/cpa/platform/common/util/PlayerData;
     109: invokevirtual #226                // Method com/github/razorplay01/cpa/platform/common/util/PlayerData.getPlayerPosition:()Lnet/minecraft/class_243;
     112: invokevirtual #230                // Method com/github/razorplay01/cpa/platform/common/util/PlayerData.setPrevPlayerPosition:(Lnet/minecraft/class_243;)V
     115: aload_0
     116: getfield      #49                 // Field playerData:Lcom/github/razorplay01/cpa/platform/common/util/PlayerData;
     119: aload_0
     120: getfield      #49                 // Field playerData:Lcom/github/razorplay01/cpa/platform/common/util/PlayerData;
     123: invokevirtual #234                // Method com/github/razorplay01/cpa/platform/common/util/PlayerData.getPlayerBodyYaw:()F
     126: invokevirtual #237                // Method com/github/razorplay01/cpa/platform/common/util/PlayerData.setPrevPlayerBodyYaw:(F)V
     129: aload_0
     130: getfield      #49                 // Field playerData:Lcom/github/razorplay01/cpa/platform/common/util/PlayerData;
     133: aload_0
     134: invokevirtual #241                // Method method_24828:()Z
     137: invokevirtual #245                // Method com/github/razorplay01/cpa/platform/common/util/PlayerData.setPrevOnGround:(Z)V
     140: return

  public com.github.razorplay01.cpa.platform.common.animation.AnimationContainer getMainAnimationCPA();
    Code:
       0: aload_0
       1: getfield      #141                // Field mainAnimationContainer:Lcom/github/razorplay01/cpa/platform/common/animation/AnimationContainer;
       4: areturn

  public com.github.razorplay01.cpa.platform.common.animation.AnimationContainer getOverlayAnimationCPA();
    Code:
       0: aload_0
       1: getfield      #168                // Field overlayAnimationContainer:Lcom/github/razorplay01/cpa/platform/common/animation/AnimationContainer;
       4: areturn

  public com.github.razorplay01.cpa.platform.common.animation.AnimationContainer getSpecialAnimationCPA();
    Code:
       0: aload_0
       1: getfield      #176                // Field specialAnimationContainer:Lcom/github/razorplay01/cpa/platform/common/animation/AnimationContainer;
       4: areturn

  public com.github.razorplay01.cpa.platform.common.util.records.AnimationContext getAnimationContext();
    Code:
       0: aload_0
       1: getfield      #204                // Field actualAnimationContext:Lcom/github/razorplay01/cpa/platform/common/util/records/AnimationContext;
       4: areturn

  public void disableBodyPartAnimation(com.github.razorplay01.cpa.platform.common.animation.AnimationContainer, com.github.razorplay01.cpa.platform.common.util.enums.BodyParts);
    Code:
       0: aload_1
       1: invokevirtual #259                // Method com/github/razorplay01/cpa/platform/common/animation/AnimationContainer.getDisabledBoneIds:()Ljava/util/Set;
       4: aload_2
       5: invokevirtual #264                // Method com/github/razorplay01/cpa/platform/common/util/enums/BodyParts.getPartId:()Ljava/lang/String;
       8: invokeinterface #270,  2          // InterfaceMethod java/util/Set.add:(Ljava/lang/Object;)Z
      13: pop
      14: return

  public void disableBodyPartAnimationInAllContainers(com.github.razorplay01.cpa.platform.common.util.enums.BodyParts);
    Code:
       0: aload_0
       1: aload_0
       2: getfield      #141                // Field mainAnimationContainer:Lcom/github/razorplay01/cpa/platform/common/animation/AnimationContainer;
       5: aload_1
       6: invokevirtual #275                // Method disableBodyPartAnimation:(Lcom/github/razorplay01/cpa/platform/common/animation/AnimationContainer;Lcom/github/razorplay01/cpa/platform/common/util/enums/BodyParts;)V
       9: aload_0
      10: aload_0
      11: getfield      #168                // Field overlayAnimationContainer:Lcom/github/razorplay01/cpa/platform/common/animation/AnimationContainer;
      14: aload_1
      15: invokevirtual #275                // Method disableBodyPartAnimation:(Lcom/github/razorplay01/cpa/platform/common/animation/AnimationContainer;Lcom/github/razorplay01/cpa/platform/common/util/enums/BodyParts;)V
      18: aload_0
      19: aload_0
      20: getfield      #176                // Field specialAnimationContainer:Lcom/github/razorplay01/cpa/platform/common/animation/AnimationContainer;
      23: aload_1
      24: invokevirtual #275                // Method disableBodyPartAnimation:(Lcom/github/razorplay01/cpa/platform/common/animation/AnimationContainer;Lcom/github/razorplay01/cpa/platform/common/util/enums/BodyParts;)V
      27: return

  public void disableActiveArm(com.github.razorplay01.cpa.platform.common.animation.AnimationContainer);
    Code:
       0: aload_0
       1: getfield      #204                // Field actualAnimationContext:Lcom/github/razorplay01/cpa/platform/common/util/records/AnimationContext;
       4: invokevirtual #280                // Method com/github/razorplay01/cpa/platform/common/util/records/AnimationContext.player:()Lnet/minecraft/class_11890;
       7: invokevirtual #286                // Method net/minecraft/class_11890.method_6058:()Lnet/minecraft/class_1268;
      10: getstatic     #292                // Field net/minecraft/class_1268.field_5808:Lnet/minecraft/class_1268;
      13: invokevirtual #295                // Method net/minecraft/class_1268.equals:(Ljava/lang/Object;)Z
      16: ifeq          52
      19: aload_0
      20: aload_1
      21: aload_0
      22: getfield      #204                // Field actualAnimationContext:Lcom/github/razorplay01/cpa/platform/common/util/records/AnimationContext;
      25: invokevirtual #280                // Method com/github/razorplay01/cpa/platform/common/util/records/AnimationContext.player:()Lnet/minecraft/class_11890;
      28: invokevirtual #299                // Method net/minecraft/class_11890.method_6068:()Lnet/minecraft/class_1306;
      31: getstatic     #305                // Field net/minecraft/class_1306.field_6183:Lnet/minecraft/class_1306;
      34: if_acmpne     43
      37: getstatic     #308                // Field com/github/razorplay01/cpa/platform/common/util/enums/BodyParts.RIGHT_ARM:Lcom/github/razorplay01/cpa/platform/common/util/enums/BodyParts;
      40: goto          46
      43: getstatic     #311                // Field com/github/razorplay01/cpa/platform/common/util/enums/BodyParts.LEFT_ARM:Lcom/github/razorplay01/cpa/platform/common/util/enums/BodyParts;
      46: invokevirtual #275                // Method disableBodyPartAnimation:(Lcom/github/razorplay01/cpa/platform/common/animation/AnimationContainer;Lcom/github/razorplay01/cpa/platform/common/util/enums/BodyParts;)V
      49: goto          82
      52: aload_0
      53: aload_1
      54: aload_0
      55: getfield      #204                // Field actualAnimationContext:Lcom/github/razorplay01/cpa/platform/common/util/records/AnimationContext;
      58: invokevirtual #280                // Method com/github/razorplay01/cpa/platform/common/util/records/AnimationContext.player:()Lnet/minecraft/class_11890;
      61: invokevirtual #299                // Method net/minecraft/class_11890.method_6068:()Lnet/minecraft/class_1306;
      64: getstatic     #305                // Field net/minecraft/class_1306.field_6183:Lnet/minecraft/class_1306;
      67: if_acmpne     76
      70: getstatic     #311                // Field com/github/razorplay01/cpa/platform/common/util/enums/BodyParts.LEFT_ARM:Lcom/github/razorplay01/cpa/platform/common/util/enums/BodyParts;
      73: goto          79
      76: getstatic     #308                // Field com/github/razorplay01/cpa/platform/common/util/enums/BodyParts.RIGHT_ARM:Lcom/github/razorplay01/cpa/platform/common/util/enums/BodyParts;
      79: invokevirtual #275                // Method disableBodyPartAnimation:(Lcom/github/razorplay01/cpa/platform/common/animation/AnimationContainer;Lcom/github/razorplay01/cpa/platform/common/util/enums/BodyParts;)V
      82: return

  public void enableBodyPartAnimation(com.github.razorplay01.cpa.platform.common.animation.AnimationContainer, com.github.razorplay01.cpa.platform.common.util.enums.BodyParts);
    Code:
       0: aload_1
       1: invokevirtual #259                // Method com/github/razorplay01/cpa/platform/common/animation/AnimationContainer.getDisabledBoneIds:()Ljava/util/Set;
       4: aload_2
       5: invokevirtual #264                // Method com/github/razorplay01/cpa/platform/common/util/enums/BodyParts.getPartId:()Ljava/lang/String;
       8: invokeinterface #315,  2          // InterfaceMethod java/util/Set.remove:(Ljava/lang/Object;)Z
      13: pop
      14: return

  public void enableBodyPartAnimationInAllContainers(com.github.razorplay01.cpa.platform.common.util.enums.BodyParts);
    Code:
       0: aload_0
       1: aload_0
       2: getfield      #141                // Field mainAnimationContainer:Lcom/github/razorplay01/cpa/platform/common/animation/AnimationContainer;
       5: aload_1
       6: invokevirtual #318                // Method enableBodyPartAnimation:(Lcom/github/razorplay01/cpa/platform/common/animation/AnimationContainer;Lcom/github/razorplay01/cpa/platform/common/util/enums/BodyParts;)V
       9: aload_0
      10: aload_0
      11: getfield      #168                // Field overlayAnimationContainer:Lcom/github/razorplay01/cpa/platform/common/animation/AnimationContainer;
      14: aload_1
      15: invokevirtual #318                // Method enableBodyPartAnimation:(Lcom/github/razorplay01/cpa/platform/common/animation/AnimationContainer;Lcom/github/razorplay01/cpa/platform/common/util/enums/BodyParts;)V
      18: aload_0
      19: aload_0
      20: getfield      #176                // Field specialAnimationContainer:Lcom/github/razorplay01/cpa/platform/common/animation/AnimationContainer;
      23: aload_1
      24: invokevirtual #318                // Method enableBodyPartAnimation:(Lcom/github/razorplay01/cpa/platform/common/animation/AnimationContainer;Lcom/github/razorplay01/cpa/platform/common/util/enums/BodyParts;)V
      27: return

  public void forceEnableBodyPart(com.github.razorplay01.cpa.platform.common.util.enums.BodyParts);
    Code:
       0: aload_1
       1: invokevirtual #264                // Method com/github/razorplay01/cpa/platform/common/util/enums/BodyParts.getPartId:()Ljava/lang/String;
       4: astore_2
       5: aload_0
       6: aload_1
       7: invokevirtual #321                // Method enableBodyPartAnimationInAllContainers:(Lcom/github/razorplay01/cpa/platform/common/util/enums/BodyParts;)V
      10: aload_0
      11: aload_0
      12: getfield      #141                // Field mainAnimationContainer:Lcom/github/razorplay01/cpa/platform/common/animation/AnimationContainer;
      15: aload_2
      16: invokevirtual #325                // Method cpa$updateAnimationControllerForEnable:(Lcom/github/razorplay01/cpa/platform/common/animation/AnimationContainer;Ljava/lang/String;)V
      19: aload_0
      20: aload_0
      21: getfield      #168                // Field overlayAnimationContainer:Lcom/github/razorplay01/cpa/platform/common/animation/AnimationContainer;
      24: aload_2
      25: invokevirtual #325                // Method cpa$updateAnimationControllerForEnable:(Lcom/github/razorplay01/cpa/platform/common/animation/AnimationContainer;Ljava/lang/String;)V
      28: aload_0
      29: aload_0
      30: getfield      #176                // Field specialAnimationContainer:Lcom/github/razorplay01/cpa/platform/common/animation/AnimationContainer;
      33: aload_2
      34: invokevirtual #325                // Method cpa$updateAnimationControllerForEnable:(Lcom/github/razorplay01/cpa/platform/common/animation/AnimationContainer;Ljava/lang/String;)V
      37: aload_0
      38: invokevirtual #328                // Method cpa$forceAnimationRefresh:()V
      41: return

  public net.minecraft.class_572$class_573 getMainArmPose();
    Code:
       0: aload_0
       1: getfield      #49                 // Field playerData:Lcom/github/razorplay01/cpa/platform/common/util/PlayerData;
       4: invokevirtual #334                // Method com/github/razorplay01/cpa/platform/common/util/PlayerData.getMainArmPose:()Lnet/minecraft/class_572$class_573;
       7: areturn

  public void setMainArmPose(net.minecraft.class_572$class_573);
    Code:
       0: aload_0
       1: getfield      #49                 // Field playerData:Lcom/github/razorplay01/cpa/platform/common/util/PlayerData;
       4: aload_1
       5: invokevirtual #339                // Method com/github/razorplay01/cpa/platform/common/util/PlayerData.setMainArmPose:(Lnet/minecraft/class_572$class_573;)V
       8: return

  public net.minecraft.class_572$class_573 getOffArmPose();
    Code:
       0: aload_0
       1: getfield      #49                 // Field playerData:Lcom/github/razorplay01/cpa/platform/common/util/PlayerData;
       4: invokevirtual #343                // Method com/github/razorplay01/cpa/platform/common/util/PlayerData.getOffArmPose:()Lnet/minecraft/class_572$class_573;
       7: areturn

  public void setOffArmPose(net.minecraft.class_572$class_573);
    Code:
       0: aload_0
       1: getfield      #49                 // Field playerData:Lcom/github/razorplay01/cpa/platform/common/util/PlayerData;
       4: aload_1
       5: invokevirtual #346                // Method com/github/razorplay01/cpa/platform/common/util/PlayerData.setOffArmPose:(Lnet/minecraft/class_572$class_573;)V
       8: return

  private void updateAnimationSpeeds();
    Code:
       0: aload_0
       1: getfield      #141                // Field mainAnimationContainer:Lcom/github/razorplay01/cpa/platform/common/animation/AnimationContainer;
       4: invokevirtual #350                // Method com/github/razorplay01/cpa/platform/common/animation/AnimationContainer.getAnimationModifiers:()Ljava/util/HashMap;
       7: getstatic     #98                 // Field com/github/razorplay01/cpa/platform/common/util/enums/Modifiers.SPEED_MODIFIER:Lcom/github/razorplay01/cpa/platform/common/util/enums/Modifiers;
      10: invokevirtual #92                 // Method com/github/razorplay01/cpa/platform/common/util/enums/Modifiers.getModifierId:()Ljava/lang/String;
      13: invokevirtual #354                // Method java/util/HashMap.get:(Ljava/lang/Object;)Ljava/lang/Object;
      16: checkcast     #100                // class com/zigythebird/playeranimcore/animation/layered/modifier/SpeedModifier
      19: aload_0
      20: getfield      #141                // Field mainAnimationContainer:Lcom/github/razorplay01/cpa/platform/common/animation/AnimationContainer;
      23: invokevirtual #357                // Method com/github/razorplay01/cpa/platform/common/animation/AnimationContainer.getAnimationSpeed:()F
      26: getstatic     #361                // Field com/github/razorplay01/cpa/ModTemplate.CONFIG:Lcom/github/razorplay01/cpa/platform/common/config/ClientConfig;
      29: invokevirtual #365                // Method com/github/razorplay01/cpa/platform/common/config/ClientConfig.getGeneral:()Lcom/github/razorplay01/cpa/platform/common/config/ClientConfig$General;
      32: invokevirtual #368                // Method com/github/razorplay01/cpa/platform/common/config/ClientConfig$General.getAnimationSpeedMultiplier:()F
      35: fmul
      36: putfield      #372                // Field com/zigythebird/playeranimcore/animation/layered/modifier/SpeedModifier.speed:F
      39: aload_0
      40: getfield      #168                // Field overlayAnimationContainer:Lcom/github/razorplay01/cpa/platform/common/animation/AnimationContainer;
      43: invokevirtual #350                // Method com/github/razorplay01/cpa/platform/common/animation/AnimationContainer.getAnimationModifiers:()Ljava/util/HashMap;
      46: getstatic     #98                 // Field com/github/razorplay01/cpa/platform/common/util/enums/Modifiers.SPEED_MODIFIER:Lcom/github/razorplay01/cpa/platform/common/util/enums/Modifiers;
      49: invokevirtual #92                 // Method com/github/razorplay01/cpa/platform/common/util/enums/Modifiers.getModifierId:()Ljava/lang/String;
      52: invokevirtual #354                // Method java/util/HashMap.get:(Ljava/lang/Object;)Ljava/lang/Object;
      55: checkcast     #100                // class com/zigythebird/playeranimcore/animation/layered/modifier/SpeedModifier
      58: aload_0
      59: getfield      #168                // Field overlayAnimationContainer:Lcom/github/razorplay01/cpa/platform/common/animation/AnimationContainer;
      62: invokevirtual #357                // Method com/github/razorplay01/cpa/platform/common/animation/AnimationContainer.getAnimationSpeed:()F
      65: getstatic     #361                // Field com/github/razorplay01/cpa/ModTemplate.CONFIG:Lcom/github/razorplay01/cpa/platform/common/config/ClientConfig;
      68: invokevirtual #365                // Method com/github/razorplay01/cpa/platform/common/config/ClientConfig.getGeneral:()Lcom/github/razorplay01/cpa/platform/common/config/ClientConfig$General;
      71: invokevirtual #368                // Method com/github/razorplay01/cpa/platform/common/config/ClientConfig$General.getAnimationSpeedMultiplier:()F
      74: fmul
      75: putfield      #372                // Field com/zigythebird/playeranimcore/animation/layered/modifier/SpeedModifier.speed:F
      78: aload_0
      79: getfield      #176                // Field specialAnimationContainer:Lcom/github/razorplay01/cpa/platform/common/animation/AnimationContainer;
      82: invokevirtual #350                // Method com/github/razorplay01/cpa/platform/common/animation/AnimationContainer.getAnimationModifiers:()Ljava/util/HashMap;
      85: getstatic     #98                 // Field com/github/razorplay01/cpa/platform/common/util/enums/Modifiers.SPEED_MODIFIER:Lcom/github/razorplay01/cpa/platform/common/util/enums/Modifiers;
      88: invokevirtual #92                 // Method com/github/razorplay01/cpa/platform/common/util/enums/Modifiers.getModifierId:()Ljava/lang/String;
      91: invokevirtual #354                // Method java/util/HashMap.get:(Ljava/lang/Object;)Ljava/lang/Object;
      94: checkcast     #100                // class com/zigythebird/playeranimcore/animation/layered/modifier/SpeedModifier
      97: aload_0
      98: getfield      #176                // Field specialAnimationContainer:Lcom/github/razorplay01/cpa/platform/common/animation/AnimationContainer;
     101: invokevirtual #357                // Method com/github/razorplay01/cpa/platform/common/animation/AnimationContainer.getAnimationSpeed:()F
     104: getstatic     #361                // Field com/github/razorplay01/cpa/ModTemplate.CONFIG:Lcom/github/razorplay01/cpa/platform/common/config/ClientConfig;
     107: invokevirtual #365                // Method com/github/razorplay01/cpa/platform/common/config/ClientConfig.getGeneral:()Lcom/github/razorplay01/cpa/platform/common/config/ClientConfig$General;
     110: invokevirtual #368                // Method com/github/razorplay01/cpa/platform/common/config/ClientConfig$General.getAnimationSpeedMultiplier:()F
     113: fmul
     114: putfield      #372                // Field com/zigythebird/playeranimcore/animation/layered/modifier/SpeedModifier.speed:F
     117: return

  private void enableAllBodyPartsInAllContainers();
    Code:
       0: aload_0
       1: aload_0
       2: getfield      #141                // Field mainAnimationContainer:Lcom/github/razorplay01/cpa/platform/common/animation/AnimationContainer;
       5: invokevirtual #375                // Method cpa$enabledAllBodyPartsAnimation:(Lcom/github/razorplay01/cpa/platform/common/animation/AnimationContainer;)V
       8: aload_0
       9: aload_0
      10: getfield      #168                // Field overlayAnimationContainer:Lcom/github/razorplay01/cpa/platform/common/animation/AnimationContainer;
      13: invokevirtual #375                // Method cpa$enabledAllBodyPartsAnimation:(Lcom/github/razorplay01/cpa/platform/common/animation/AnimationContainer;)V
      16: aload_0
      17: aload_0
      18: getfield      #176                // Field specialAnimationContainer:Lcom/github/razorplay01/cpa/platform/common/animation/AnimationContainer;
      21: invokevirtual #375                // Method cpa$enabledAllBodyPartsAnimation:(Lcom/github/razorplay01/cpa/platform/common/animation/AnimationContainer;)V
      24: return

  private void cpa$enabledAllBodyPartsAnimation(com.github.razorplay01.cpa.platform.common.animation.AnimationContainer);
    Code:
       0: aload_1
       1: invokevirtual #379                // Method com/github/razorplay01/cpa/platform/common/animation/AnimationContainer.getAnimationController:()Lcom/zigythebird/playeranimcore/animation/AnimationController;
       4: invokedynamic #398,  0            // InvokeDynamic #0:accept:()Ljava/util/function/Consumer;
       9: invokevirtual #402                // Method com/zigythebird/playeranimcore/animation/AnimationController.setPostAnimationSetupConsumer:(Ljava/util/function/Consumer;)Lcom/zigythebird/playeranimcore/animation/AnimationController;
      12: pop
      13: aload_1
      14: invokevirtual #259                // Method com/github/razorplay01/cpa/platform/common/animation/AnimationContainer.getDisabledBoneIds:()Ljava/util/Set;
      17: invokeinterface #405,  1          // InterfaceMethod java/util/Set.clear:()V
      22: return

  private void applyDisables();
    Code:
       0: aload_0
       1: aload_0
       2: getfield      #141                // Field mainAnimationContainer:Lcom/github/razorplay01/cpa/platform/common/animation/AnimationContainer;
       5: invokevirtual #408                // Method cpa$applyDisableToContainer:(Lcom/github/razorplay01/cpa/platform/common/animation/AnimationContainer;)V
       8: aload_0
       9: aload_0
      10: getfield      #168                // Field overlayAnimationContainer:Lcom/github/razorplay01/cpa/platform/common/animation/AnimationContainer;
      13: invokevirtual #408                // Method cpa$applyDisableToContainer:(Lcom/github/razorplay01/cpa/platform/common/animation/AnimationContainer;)V
      16: aload_0
      17: aload_0
      18: getfield      #176                // Field specialAnimationContainer:Lcom/github/razorplay01/cpa/platform/common/animation/AnimationContainer;
      21: invokevirtual #408                // Method cpa$applyDisableToContainer:(Lcom/github/razorplay01/cpa/platform/common/animation/AnimationContainer;)V
      24: return

  private void cpa$preserveOnlyHeadRoll(java.util.function.Function<java.lang.String, com.zigythebird.playeranimcore.bones.AdvancedPlayerAnimBone>, java.util.Set<java.lang.String>);
    Code:
       0: getstatic     #416                // Field com/github/razorplay01/cpa/platform/common/util/enums/BodyParts.HEAD:Lcom/github/razorplay01/cpa/platform/common/util/enums/BodyParts;
       3: invokevirtual #264                // Method com/github/razorplay01/cpa/platform/common/util/enums/BodyParts.getPartId:()Ljava/lang/String;
       6: astore_3
       7: aload_2
       8: aload_3
       9: invokeinterface #419,  2          // InterfaceMethod java/util/Set.contains:(Ljava/lang/Object;)Z
      14: ifeq          18
      17: return
      18: aload_1
      19: aload_3
      20: invokeinterface #426,  2          // InterfaceMethod java/util/function/Function.apply:(Ljava/lang/Object;)Ljava/lang/Object;
      25: checkcast     #428                // class com/zigythebird/playeranimcore/bones/AdvancedPlayerAnimBone
      28: astore        4
      30: aload         4
      32: ifnonnull     36
      35: return
      36: aload         4
      38: iconst_0
      39: putfield      #432                // Field com/zigythebird/playeranimcore/bones/AdvancedPlayerAnimBone.rotXEnabled:Z
      42: aload         4
      44: iconst_0
      45: putfield      #435                // Field com/zigythebird/playeranimcore/bones/AdvancedPlayerAnimBone.rotYEnabled:Z
      48: aload         4
      50: iconst_1
      51: putfield      #438                // Field com/zigythebird/playeranimcore/bones/AdvancedPlayerAnimBone.rotZEnabled:Z
      54: return

  private void cpa$applyDisableToContainer(com.github.razorplay01.cpa.platform.common.animation.AnimationContainer);
    Code:
       0: aload_1
       1: invokevirtual #259                // Method com/github/razorplay01/cpa/platform/common/animation/AnimationContainer.getDisabledBoneIds:()Ljava/util/Set;
       4: astore_2
       5: aload_2
       6: invokeinterface #449,  1          // InterfaceMethod java/util/Set.isEmpty:()Z
      11: ifeq          32
      14: aload_1
      15: invokevirtual #379                // Method com/github/razorplay01/cpa/platform/common/animation/AnimationContainer.getAnimationController:()Lcom/zigythebird/playeranimcore/animation/AnimationController;
      18: aload_0
      19: aload_2
      20: invokedynamic #457,  0            // InvokeDynamic #1:accept:(Lcom/github/razorplay01/cpa/mixin/AbstractClientPlayerEntityMixin;Ljava/util/Set;)Ljava/util/function/Consumer;
      25: invokevirtual #402                // Method com/zigythebird/playeranimcore/animation/AnimationController.setPostAnimationSetupConsumer:(Ljava/util/function/Consumer;)Lcom/zigythebird/playeranimcore/animation/AnimationController;
      28: pop
      29: goto          47
      32: aload_1
      33: invokevirtual #379                // Method com/github/razorplay01/cpa/platform/common/animation/AnimationContainer.getAnimationController:()Lcom/zigythebird/playeranimcore/animation/AnimationController;
      36: aload_0
      37: aload_2
      38: invokedynamic #462,  0            // InvokeDynamic #2:accept:(Lcom/github/razorplay01/cpa/mixin/AbstractClientPlayerEntityMixin;Ljava/util/Set;)Ljava/util/function/Consumer;
      43: invokevirtual #402                // Method com/zigythebird/playeranimcore/animation/AnimationController.setPostAnimationSetupConsumer:(Ljava/util/function/Consumer;)Lcom/zigythebird/playeranimcore/animation/AnimationController;
      46: pop
      47: return

  private void cpa$updateAnimationControllerForEnable(com.github.razorplay01.cpa.platform.common.animation.AnimationContainer, java.lang.String);
    Code:
       0: aload_1
       1: invokevirtual #379                // Method com/github/razorplay01/cpa/platform/common/animation/AnimationContainer.getAnimationController:()Lcom/zigythebird/playeranimcore/animation/AnimationController;
       4: aload_2
       5: aload_1
       6: invokedynamic #470,  0            // InvokeDynamic #3:accept:(Ljava/lang/String;Lcom/github/razorplay01/cpa/platform/common/animation/AnimationContainer;)Ljava/util/function/Consumer;
      11: invokevirtual #402                // Method com/zigythebird/playeranimcore/animation/AnimationController.setPostAnimationSetupConsumer:(Ljava/util/function/Consumer;)Lcom/zigythebird/playeranimcore/animation/AnimationController;
      14: pop
      15: return

  private void cpa$forceAnimationRefresh();
    Code:
       0: aload_0
       1: aload_0
       2: getfield      #141                // Field mainAnimationContainer:Lcom/github/razorplay01/cpa/platform/common/animation/AnimationContainer;
       5: invokevirtual #474                // Method cpa$getCurrentAnimation:(Lcom/github/razorplay01/cpa/platform/common/animation/AnimationContainer;)Lcom/zigythebird/playeranimcore/animation/Animation;
       8: astore_1
       9: aload_0
      10: aload_0
      11: getfield      #168                // Field overlayAnimationContainer:Lcom/github/razorplay01/cpa/platform/common/animation/AnimationContainer;
      14: invokevirtual #474                // Method cpa$getCurrentAnimation:(Lcom/github/razorplay01/cpa/platform/common/animation/AnimationContainer;)Lcom/zigythebird/playeranimcore/animation/Animation;
      17: astore_2
      18: aload_0
      19: aload_0
      20: getfield      #176                // Field specialAnimationContainer:Lcom/github/razorplay01/cpa/platform/common/animation/AnimationContainer;
      23: invokevirtual #474                // Method cpa$getCurrentAnimation:(Lcom/github/razorplay01/cpa/platform/common/animation/AnimationContainer;)Lcom/zigythebird/playeranimcore/animation/Animation;
      26: astore_3
      27: getstatic     #127                // Field com/github/razorplay01/cpa/platform/common/util/enums/AnimationsId.BLANK_LOOP_ANIMATION:Lcom/github/razorplay01/cpa/platform/common/util/enums/AnimationsId;
      30: invokevirtual #130                // Method com/github/razorplay01/cpa/platform/common/util/enums/AnimationsId.getAnimationId:()Ljava/lang/String;
      33: invokestatic  #134                // Method com/github/razorplay01/cpa/ModTemplate.getAnimation:(Ljava/lang/String;)Lcom/zigythebird/playeranimcore/animation/Animation;
      36: astore        4
      38: aload_0
      39: aload_0
      40: getfield      #141                // Field mainAnimationContainer:Lcom/github/razorplay01/cpa/platform/common/animation/AnimationContainer;
      43: aload         4
      45: iconst_1
      46: invokevirtual #478                // Method cpa$replaceAnimationSafely:(Lcom/github/razorplay01/cpa/platform/common/animation/AnimationContainer;Lcom/zigythebird/playeranimcore/animation/Animation;I)V
      49: aload_0
      50: aload_0
      51: getfield      #168                // Field overlayAnimationContainer:Lcom/github/razorplay01/cpa/platform/common/animation/AnimationContainer;
      54: aload         4
      56: iconst_1
      57: invokevirtual #478                // Method cpa$replaceAnimationSafely:(Lcom/github/razorplay01/cpa/platform/common/animation/AnimationContainer;Lcom/zigythebird/playeranimcore/animation/Animation;I)V
      60: aload_0
      61: aload_0
      62: getfield      #176                // Field specialAnimationContainer:Lcom/github/razorplay01/cpa/platform/common/animation/AnimationContainer;
      65: aload         4
      67: iconst_1
      68: invokevirtual #478                // Method cpa$replaceAnimationSafely:(Lcom/github/razorplay01/cpa/platform/common/animation/AnimationContainer;Lcom/zigythebird/playeranimcore/animation/Animation;I)V
      71: aload_1
      72: ifnull        85
      75: aload_0
      76: aload_0
      77: getfield      #141                // Field mainAnimationContainer:Lcom/github/razorplay01/cpa/platform/common/animation/AnimationContainer;
      80: aload_1
      81: iconst_2
      82: invokevirtual #478                // Method cpa$replaceAnimationSafely:(Lcom/github/razorplay01/cpa/platform/common/animation/AnimationContainer;Lcom/zigythebird/playeranimcore/animation/Animation;I)V
      85: aload_2
      86: ifnull        99
      89: aload_0
      90: aload_0
      91: getfield      #168                // Field overlayAnimationContainer:Lcom/github/razorplay01/cpa/platform/common/animation/AnimationContainer;
      94: aload_2
      95: iconst_2
      96: invokevirtual #478                // Method cpa$replaceAnimationSafely:(Lcom/github/razorplay01/cpa/platform/common/animation/AnimationContainer;Lcom/zigythebird/playeranimcore/animation/Animation;I)V
      99: aload_3
     100: ifnull        113
     103: aload_0
     104: aload_0
     105: getfield      #176                // Field specialAnimationContainer:Lcom/github/razorplay01/cpa/platform/common/animation/AnimationContainer;
     108: aload_3
     109: iconst_2
     110: invokevirtual #478                // Method cpa$replaceAnimationSafely:(Lcom/github/razorplay01/cpa/platform/common/animation/AnimationContainer;Lcom/zigythebird/playeranimcore/animation/Animation;I)V
     113: return

  private com.zigythebird.playeranimcore.animation.Animation cpa$getCurrentAnimation(com.github.razorplay01.cpa.platform.common.animation.AnimationContainer);
    Code:
       0: aload_1
       1: invokevirtual #379                // Method com/github/razorplay01/cpa/platform/common/animation/AnimationContainer.getAnimationController:()Lcom/zigythebird/playeranimcore/animation/AnimationController;
       4: invokevirtual #489                // Method com/zigythebird/playeranimcore/animation/AnimationController.getCurrentAnimation:()Lcom/zigythebird/playeranimcore/animation/QueuedAnimation;
       7: astore_2
       8: aload_2
       9: ifnull        17
      12: aload_2
      13: invokevirtual #495                // Method com/zigythebird/playeranimcore/animation/QueuedAnimation.animation:()Lcom/zigythebird/playeranimcore/animation/Animation;
      16: areturn
      17: aconst_null
      18: areturn

  private void cpa$replaceAnimationSafely(com.github.razorplay01.cpa.platform.common.animation.AnimationContainer, com.zigythebird.playeranimcore.animation.Animation, int);
    Code:
       0: aload_1
       1: invokevirtual #379                // Method com/github/razorplay01/cpa/platform/common/animation/AnimationContainer.getAnimationController:()Lcom/zigythebird/playeranimcore/animation/AnimationController;
       4: iload_3
       5: getstatic     #504                // Field com/zigythebird/playeranimcore/easing/EasingType.EASE_IN_OUT_SINE:Lcom/zigythebird/playeranimcore/easing/EasingType;
       8: invokestatic  #510                // Method com/zigythebird/playeranimcore/animation/layered/modifier/AbstractFadeModifier.standardFadeIn:(ILcom/zigythebird/playeranimcore/easing/EasingType;)Lcom/zigythebird/playeranimcore/animation/layered/modifier/AbstractFadeModifier;
      11: aload_2
      12: iconst_0
      13: invokevirtual #514                // Method com/zigythebird/playeranimcore/animation/AnimationController.replaceAnimationWithFade:(Lcom/zigythebird/playeranimcore/animation/layered/modifier/AbstractFadeModifier;Lcom/zigythebird/playeranimcore/animation/Animation;Z)V
      16: return

  private void playAnimations();
    Code:
       0: getstatic     #521                // Field com/github/razorplay01/cpa/platform/common/animation/animations/AnimationProvider.MAIN_ANIMATIONS:Ljava/util/List;
       3: invokeinterface #527,  1          // InterfaceMethod java/util/List.iterator:()Ljava/util/Iterator;
       8: astore_1
       9: aload_1
      10: invokeinterface #532,  1          // InterfaceMethod java/util/Iterator.hasNext:()Z
      15: ifeq          54
      18: aload_1
      19: invokeinterface #536,  1          // InterfaceMethod java/util/Iterator.next:()Ljava/lang/Object;
      24: checkcast     #538                // class com/github/razorplay01/cpa/platform/common/util/interfaces/ICustomAnimation
      27: astore_2
      28: aload_2
      29: aload_0
      30: getfield      #204                // Field actualAnimationContext:Lcom/github/razorplay01/cpa/platform/common/util/records/AnimationContext;
      33: invokeinterface #542,  2          // InterfaceMethod com/github/razorplay01/cpa/platform/common/util/interfaces/ICustomAnimation.shouldPlayAnimation:(Lcom/github/razorplay01/cpa/platform/common/util/records/AnimationContext;)Z
      38: ifeq          51
      41: aload_2
      42: aload_0
      43: getfield      #204                // Field actualAnimationContext:Lcom/github/razorplay01/cpa/platform/common/util/records/AnimationContext;
      46: invokeinterface #546,  2          // InterfaceMethod com/github/razorplay01/cpa/platform/common/util/interfaces/ICustomAnimation.playAnimation:(Lcom/github/razorplay01/cpa/platform/common/util/records/AnimationContext;)V
      51: goto          9
      54: getstatic     #549                // Field com/github/razorplay01/cpa/platform/common/animation/animations/AnimationProvider.OVERLAY_ANIMATIONS:Ljava/util/List;
      57: invokeinterface #527,  1          // InterfaceMethod java/util/List.iterator:()Ljava/util/Iterator;
      62: astore_1
      63: aload_1
      64: invokeinterface #532,  1          // InterfaceMethod java/util/Iterator.hasNext:()Z
      69: ifeq          108
      72: aload_1
      73: invokeinterface #536,  1          // InterfaceMethod java/util/Iterator.next:()Ljava/lang/Object;
      78: checkcast     #538                // class com/github/razorplay01/cpa/platform/common/util/interfaces/ICustomAnimation
      81: astore_2
      82: aload_2
      83: aload_0
      84: getfield      #204                // Field actualAnimationContext:Lcom/github/razorplay01/cpa/platform/common/util/records/AnimationContext;
      87: invokeinterface #542,  2          // InterfaceMethod com/github/razorplay01/cpa/platform/common/util/interfaces/ICustomAnimation.shouldPlayAnimation:(Lcom/github/razorplay01/cpa/platform/common/util/records/AnimationContext;)Z
      92: ifeq          105
      95: aload_2
      96: aload_0
      97: getfield      #204                // Field actualAnimationContext:Lcom/github/razorplay01/cpa/platform/common/util/records/AnimationContext;
     100: invokeinterface #546,  2          // InterfaceMethod com/github/razorplay01/cpa/platform/common/util/interfaces/ICustomAnimation.playAnimation:(Lcom/github/razorplay01/cpa/platform/common/util/records/AnimationContext;)V
     105: goto          63
     108: getstatic     #552                // Field com/github/razorplay01/cpa/platform/common/animation/animations/AnimationProvider.SPECIAL_ANIMATIONS:Ljava/util/List;
     111: invokeinterface #527,  1          // InterfaceMethod java/util/List.iterator:()Ljava/util/Iterator;
     116: astore_1
     117: aload_1
     118: invokeinterface #532,  1          // InterfaceMethod java/util/Iterator.hasNext:()Z
     123: ifeq          162
     126: aload_1
     127: invokeinterface #536,  1          // InterfaceMethod java/util/Iterator.next:()Ljava/lang/Object;
     132: checkcast     #538                // class com/github/razorplay01/cpa/platform/common/util/interfaces/ICustomAnimation
     135: astore_2
     136: aload_2
     137: aload_0
     138: getfield      #204                // Field actualAnimationContext:Lcom/github/razorplay01/cpa/platform/common/util/records/AnimationContext;
     141: invokeinterface #542,  2          // InterfaceMethod com/github/razorplay01/cpa/platform/common/util/interfaces/ICustomAnimation.shouldPlayAnimation:(Lcom/github/razorplay01/cpa/platform/common/util/records/AnimationContext;)Z
     146: ifeq          159
     149: aload_2
     150: aload_0
     151: getfield      #204                // Field actualAnimationContext:Lcom/github/razorplay01/cpa/platform/common/util/records/AnimationContext;
     154: invokeinterface #546,  2          // InterfaceMethod com/github/razorplay01/cpa/platform/common/util/interfaces/ICustomAnimation.playAnimation:(Lcom/github/razorplay01/cpa/platform/common/util/records/AnimationContext;)V
     159: goto          117
     162: return

  private void updateAnimationContainers();
    Code:
       0: aload_0
       1: aload_0
       2: getfield      #141                // Field mainAnimationContainer:Lcom/github/razorplay01/cpa/platform/common/animation/AnimationContainer;
       5: invokevirtual #556                // Method updateAnimationContainer:(Lcom/github/razorplay01/cpa/platform/common/animation/AnimationContainer;)V
       8: aload_0
       9: aload_0
      10: getfield      #168                // Field overlayAnimationContainer:Lcom/github/razorplay01/cpa/platform/common/animation/AnimationContainer;
      13: invokevirtual #556                // Method updateAnimationContainer:(Lcom/github/razorplay01/cpa/platform/common/animation/AnimationContainer;)V
      16: aload_0
      17: aload_0
      18: getfield      #176                // Field specialAnimationContainer:Lcom/github/razorplay01/cpa/platform/common/animation/AnimationContainer;
      21: invokevirtual #556                // Method updateAnimationContainer:(Lcom/github/razorplay01/cpa/platform/common/animation/AnimationContainer;)V
      24: return

  private void updateAnimationContainer(com.github.razorplay01.cpa.platform.common.animation.AnimationContainer);
    Code:
       0: aload_1
       1: invokevirtual #379                // Method com/github/razorplay01/cpa/platform/common/animation/AnimationContainer.getAnimationController:()Lcom/zigythebird/playeranimcore/animation/AnimationController;
       4: invokevirtual #559                // Method com/zigythebird/playeranimcore/animation/AnimationController.isActive:()Z
       7: ifne          64
      10: aload_1
      11: invokevirtual #562                // Method com/github/razorplay01/cpa/platform/common/animation/AnimationContainer.getCurrentAnimationId:()Ljava/lang/String;
      14: getstatic     #127                // Field com/github/razorplay01/cpa/platform/common/util/enums/AnimationsId.BLANK_LOOP_ANIMATION:Lcom/github/razorplay01/cpa/platform/common/util/enums/AnimationsId;
      17: invokevirtual #130                // Method com/github/razorplay01/cpa/platform/common/util/enums/AnimationsId.getAnimationId:()Ljava/lang/String;
      20: invokevirtual #563                // Method java/lang/String.equals:(Ljava/lang/Object;)Z
      23: ifne          64
      26: aload_1
      27: getstatic     #127                // Field com/github/razorplay01/cpa/platform/common/util/enums/AnimationsId.BLANK_LOOP_ANIMATION:Lcom/github/razorplay01/cpa/platform/common/util/enums/AnimationsId;
      30: invokevirtual #130                // Method com/github/razorplay01/cpa/platform/common/util/enums/AnimationsId.getAnimationId:()Ljava/lang/String;
      33: invokestatic  #134                // Method com/github/razorplay01/cpa/ModTemplate.getAnimation:(Ljava/lang/String;)Lcom/zigythebird/playeranimcore/animation/Animation;
      36: invokevirtual #567                // Method com/github/razorplay01/cpa/platform/common/animation/AnimationContainer.setCurrentAnimation:(Lcom/zigythebird/playeranimcore/animation/Animation;)V
      39: aload_1
      40: getstatic     #127                // Field com/github/razorplay01/cpa/platform/common/util/enums/AnimationsId.BLANK_LOOP_ANIMATION:Lcom/github/razorplay01/cpa/platform/common/util/enums/AnimationsId;
      43: invokevirtual #130                // Method com/github/razorplay01/cpa/platform/common/util/enums/AnimationsId.getAnimationId:()Ljava/lang/String;
      46: invokevirtual #571                // Method com/github/razorplay01/cpa/platform/common/animation/AnimationContainer.setCurrentAnimationId:(Ljava/lang/String;)V
      49: aload_1
      50: iconst_0
      51: invokevirtual #575                // Method com/github/razorplay01/cpa/platform/common/animation/AnimationContainer.setAnimationPriority:(I)V
      54: aload_1
      55: iconst_0
      56: invokevirtual #578                // Method com/github/razorplay01/cpa/platform/common/animation/AnimationContainer.setAnimationFadeTime:(I)V
      59: aload_1
      60: fconst_1
      61: invokevirtual #581                // Method com/github/razorplay01/cpa/platform/common/animation/AnimationContainer.setAnimationSpeed:(F)V
      64: aload_1
      65: invokevirtual #562                // Method com/github/razorplay01/cpa/platform/common/animation/AnimationContainer.getCurrentAnimationId:()Ljava/lang/String;
      68: aload_1
      69: invokevirtual #584                // Method com/github/razorplay01/cpa/platform/common/animation/AnimationContainer.getPrevAnimationId:()Ljava/lang/String;
      72: invokestatic  #589                // Method java/util/Objects.equals:(Ljava/lang/Object;Ljava/lang/Object;)Z
      75: ifne          89
      78: aload_1
      79: invokevirtual #593                // Method com/github/razorplay01/cpa/platform/common/animation/AnimationContainer.getAnimationPriority:()I
      82: aload_1
      83: invokevirtual #596                // Method com/github/razorplay01/cpa/platform/common/animation/AnimationContainer.getPrevAnimationPriority:()I
      86: if_icmpge     99
      89: aload_1
      90: invokevirtual #379                // Method com/github/razorplay01/cpa/platform/common/animation/AnimationContainer.getAnimationController:()Lcom/zigythebird/playeranimcore/animation/AnimationController;
      93: invokevirtual #559                // Method com/zigythebird/playeranimcore/animation/AnimationController.isActive:()Z
      96: ifne          120
      99: aload_0
     100: aload_1
     101: invokevirtual #599                // Method playCurrentAnimation:(Lcom/github/razorplay01/cpa/platform/common/animation/AnimationContainer;)V
     104: aload_1
     105: aload_1
     106: invokevirtual #562                // Method com/github/razorplay01/cpa/platform/common/animation/AnimationContainer.getCurrentAnimationId:()Ljava/lang/String;
     109: invokevirtual #602                // Method com/github/razorplay01/cpa/platform/common/animation/AnimationContainer.setPrevAnimationId:(Ljava/lang/String;)V
     112: aload_1
     113: aload_1
     114: invokevirtual #593                // Method com/github/razorplay01/cpa/platform/common/animation/AnimationContainer.getAnimationPriority:()I
     117: invokevirtual #605                // Method com/github/razorplay01/cpa/platform/common/animation/AnimationContainer.setPrevAnimationPriority:(I)V
     120: return

  public void playCurrentAnimation(com.github.razorplay01.cpa.platform.common.animation.AnimationContainer);
    Code:
       0: aload_1
       1: invokevirtual #379                // Method com/github/razorplay01/cpa/platform/common/animation/AnimationContainer.getAnimationController:()Lcom/zigythebird/playeranimcore/animation/AnimationController;
       4: aload_1
       5: invokevirtual #608                // Method com/github/razorplay01/cpa/platform/common/animation/AnimationContainer.getAnimationFadeTime:()I
       8: i2f
       9: getstatic     #361                // Field com/github/razorplay01/cpa/ModTemplate.CONFIG:Lcom/github/razorplay01/cpa/platform/common/config/ClientConfig;
      12: invokevirtual #365                // Method com/github/razorplay01/cpa/platform/common/config/ClientConfig.getGeneral:()Lcom/github/razorplay01/cpa/platform/common/config/ClientConfig$General;
      15: invokevirtual #611                // Method com/github/razorplay01/cpa/platform/common/config/ClientConfig$General.getAnimationFadeTimeMultiplier:()F
      18: fmul
      19: f2i
      20: getstatic     #504                // Field com/zigythebird/playeranimcore/easing/EasingType.EASE_IN_OUT_SINE:Lcom/zigythebird/playeranimcore/easing/EasingType;
      23: invokestatic  #510                // Method com/zigythebird/playeranimcore/animation/layered/modifier/AbstractFadeModifier.standardFadeIn:(ILcom/zigythebird/playeranimcore/easing/EasingType;)Lcom/zigythebird/playeranimcore/animation/layered/modifier/AbstractFadeModifier;
      26: invokestatic  #617                // Method com/zigythebird/playeranimcore/animation/RawAnimation.begin:()Lcom/zigythebird/playeranimcore/animation/RawAnimation;
      29: aload_1
      30: invokevirtual #619                // Method com/github/razorplay01/cpa/platform/common/animation/AnimationContainer.getCurrentAnimation:()Lcom/zigythebird/playeranimcore/animation/Animation;
      33: invokevirtual #623                // Method com/zigythebird/playeranimcore/animation/RawAnimation.thenPlay:(Lcom/zigythebird/playeranimcore/animation/Animation;)Lcom/zigythebird/playeranimcore/animation/RawAnimation;
      36: iconst_0
      37: invokevirtual #626                // Method com/zigythebird/playeranimcore/animation/AnimationController.replaceAnimationWithFade:(Lcom/zigythebird/playeranimcore/animation/layered/modifier/AbstractFadeModifier;Lcom/zigythebird/playeranimcore/animation/RawAnimation;Z)V
      40: return

  private void checkMainHandItemForArmDisabling();
    Code:
       0: aload_0
       1: invokevirtual #630                // Method method_6047:()Lnet/minecraft/class_1799;
       4: invokevirtual #635                // Method net/minecraft/class_1799.method_7960:()Z
       7: ifne          73
      10: aload_0
      11: invokevirtual #638                // Method method_6115:()Z
      14: ifeq          73
      17: aload_0
      18: invokevirtual #641                // Method method_31550:()Z
      21: ifne          50
      24: aload_0
      25: invokevirtual #630                // Method method_6047:()Lnet/minecraft/class_1799;
      28: invokevirtual #645                // Method net/minecraft/class_1799.method_7909:()Lnet/minecraft/class_1792;
      31: instanceof    #647                // class net/minecraft/class_7430
      34: ifne          50
      37: aload_0
      38: invokevirtual #630                // Method method_6047:()Lnet/minecraft/class_1799;
      41: invokevirtual #645                // Method net/minecraft/class_1799.method_7909:()Lnet/minecraft/class_1792;
      44: instanceof    #649                // class net/minecraft/class_8162
      47: ifeq          73
      50: aload_0
      51: aload_0
      52: invokevirtual #650                // Method method_6068:()Lnet/minecraft/class_1306;
      55: getstatic     #305                // Field net/minecraft/class_1306.field_6183:Lnet/minecraft/class_1306;
      58: if_acmpne     67
      61: getstatic     #308                // Field com/github/razorplay01/cpa/platform/common/util/enums/BodyParts.RIGHT_ARM:Lcom/github/razorplay01/cpa/platform/common/util/enums/BodyParts;
      64: goto          70
      67: getstatic     #311                // Field com/github/razorplay01/cpa/platform/common/util/enums/BodyParts.LEFT_ARM:Lcom/github/razorplay01/cpa/platform/common/util/enums/BodyParts;
      70: invokevirtual #652                // Method disableBodyPartAnimationInAllContainers:(Lcom/github/razorplay01/cpa/platform/common/util/enums/BodyParts;)V
      73: return

  private void checkOffHandItemForArmDisabling();
    Code:
       0: aload_0
       1: invokevirtual #655                // Method method_6079:()Lnet/minecraft/class_1799;
       4: invokevirtual #635                // Method net/minecraft/class_1799.method_7960:()Z
       7: ifne          73
      10: aload_0
      11: invokevirtual #638                // Method method_6115:()Z
      14: ifeq          73
      17: aload_0
      18: invokevirtual #641                // Method method_31550:()Z
      21: ifne          50
      24: aload_0
      25: invokevirtual #655                // Method method_6079:()Lnet/minecraft/class_1799;
      28: invokevirtual #645                // Method net/minecraft/class_1799.method_7909:()Lnet/minecraft/class_1792;
      31: instanceof    #647                // class net/minecraft/class_7430
      34: ifne          50
      37: aload_0
      38: invokevirtual #655                // Method method_6079:()Lnet/minecraft/class_1799;
      41: invokevirtual #645                // Method net/minecraft/class_1799.method_7909:()Lnet/minecraft/class_1792;
      44: instanceof    #649                // class net/minecraft/class_8162
      47: ifeq          73
      50: aload_0
      51: aload_0
      52: invokevirtual #650                // Method method_6068:()Lnet/minecraft/class_1306;
      55: getstatic     #305                // Field net/minecraft/class_1306.field_6183:Lnet/minecraft/class_1306;
      58: if_acmpne     67
      61: getstatic     #311                // Field com/github/razorplay01/cpa/platform/common/util/enums/BodyParts.LEFT_ARM:Lcom/github/razorplay01/cpa/platform/common/util/enums/BodyParts;
      64: goto          70
      67: getstatic     #308                // Field com/github/razorplay01/cpa/platform/common/util/enums/BodyParts.RIGHT_ARM:Lcom/github/razorplay01/cpa/platform/common/util/enums/BodyParts;
      70: invokevirtual #652                // Method disableBodyPartAnimationInAllContainers:(Lcom/github/razorplay01/cpa/platform/common/util/enums/BodyParts;)V
      73: return

  private static void lambda$cpa$updateAnimationControllerForEnable$0(java.lang.String, com.github.razorplay01.cpa.platform.common.animation.AnimationContainer, java.util.function.Function);
    Code:
       0: aload_2
       1: aload_0
       2: invokeinterface #426,  2          // InterfaceMethod java/util/function/Function.apply:(Ljava/lang/Object;)Ljava/lang/Object;
       7: checkcast     #428                // class com/zigythebird/playeranimcore/bones/AdvancedPlayerAnimBone
      10: iconst_1
      11: invokevirtual #658                // Method com/zigythebird/playeranimcore/bones/AdvancedPlayerAnimBone.setEnabled:(Z)V
      14: aload_1
      15: invokevirtual #259                // Method com/github/razorplay01/cpa/platform/common/animation/AnimationContainer.getDisabledBoneIds:()Ljava/util/Set;
      18: invokeinterface #659,  1          // InterfaceMethod java/util/Set.iterator:()Ljava/util/Iterator;
      23: astore_3
      24: aload_3
      25: invokeinterface #532,  1          // InterfaceMethod java/util/Iterator.hasNext:()Z
      30: ifeq          71
      33: aload_3
      34: invokeinterface #536,  1          // InterfaceMethod java/util/Iterator.next:()Ljava/lang/Object;
      39: checkcast     #421                // class java/lang/String
      42: astore        4
      44: aload         4
      46: aload_0
      47: invokevirtual #563                // Method java/lang/String.equals:(Ljava/lang/Object;)Z
      50: ifne          68
      53: aload_2
      54: aload         4
      56: invokeinterface #426,  2          // InterfaceMethod java/util/function/Function.apply:(Ljava/lang/Object;)Ljava/lang/Object;
      61: checkcast     #428                // class com/zigythebird/playeranimcore/bones/AdvancedPlayerAnimBone
      64: iconst_0
      65: invokevirtual #658                // Method com/zigythebird/playeranimcore/bones/AdvancedPlayerAnimBone.setEnabled:(Z)V
      68: goto          24
      71: return

  private void lambda$cpa$applyDisableToContainer$1(java.util.Set, java.util.function.Function);
    Code:
       0: aload_1
       1: invokeinterface #659,  1          // InterfaceMethod java/util/Set.iterator:()Ljava/util/Iterator;
       6: astore_3
       7: aload_3
       8: invokeinterface #532,  1          // InterfaceMethod java/util/Iterator.hasNext:()Z
      13: ifeq          51
      16: aload_3
      17: invokeinterface #536,  1          // InterfaceMethod java/util/Iterator.next:()Ljava/lang/Object;
      22: checkcast     #421                // class java/lang/String
      25: astore        4
      27: aload_2
      28: aload         4
      30: invokeinterface #426,  2          // InterfaceMethod java/util/function/Function.apply:(Ljava/lang/Object;)Ljava/lang/Object;
      35: checkcast     #428                // class com/zigythebird/playeranimcore/bones/AdvancedPlayerAnimBone
      38: iconst_0
      39: invokevirtual #658                // Method com/zigythebird/playeranimcore/bones/AdvancedPlayerAnimBone.setEnabled:(Z)V
      42: aload_0
      43: aload_2
      44: aload_1
      45: invokevirtual #664                // Method cpa$preserveOnlyHeadRoll:(Ljava/util/function/Function;Ljava/util/Set;)V
      48: goto          7
      51: return

  private void lambda$cpa$applyDisableToContainer$0(java.util.Set, java.util.function.Function);
    Code:
       0: aload_0
       1: aload_2
       2: aload_1
       3: invokevirtual #664                // Method cpa$preserveOnlyHeadRoll:(Ljava/util/function/Function;Ljava/util/Set;)V
       6: return

  private static void lambda$cpa$enabledAllBodyPartsAnimation$0(java.util.function.Function);
    Code:
       0: return
}
